{"version":1,"resource":"file:///home/nadir/dev/projects/svelte-test/index.html","entries":[{"id":"3JJV.html","timestamp":1705749685984},{"id":"Zdkl.html","timestamp":1705749785625},{"id":"bjPH.html","timestamp":1705749839347},{"id":"pZgx.html","timestamp":1705749876212},{"id":"b62P.html","timestamp":1705749957514},{"id":"kPzH.html","timestamp":1705749973977},{"id":"L1lx.html","timestamp":1705749985415},{"id":"3aVJ.html","timestamp":1705750279909},{"id":"5mUx.html","timestamp":1705750428478},{"id":"znbc.html","timestamp":1705750473320},{"id":"YrgP.html","timestamp":1705750628890},{"id":"qK87.html","timestamp":1705844392883},{"id":"gCv7.html","timestamp":1705844433857}]}